bmkg/__init__.py
bmkg/gempa.py
bmkg_gempa-1.0.1.dist-info/LICENSE
bmkg_gempa-1.0.1.dist-info/METADATA
bmkg_gempa-1.0.1.dist-info/WHEEL
bmkg_gempa-1.0.1.dist-info/top_level.txt
bmkg_gempa-1.0.1.dist-info/RECORD
