Metadata-Version: 2.1
Name: bmkg-gempa
Version: 1.0.1
Summary: Konversi data gempa bumi BMKG dari XML ke JSON.
Home-page: https://github.com/muhammadhanif/bmkg-gempa
Author: Muhammad Hanif
Author-email: moehammadhanif@gmail.com
License: UNKNOWN
Platform: UNKNOWN
Classifier: Programming Language :: Python :: 3
Classifier: License :: OSI Approved :: MIT License
Classifier: Operating System :: OS Independent
Requires-Python: >=3.6
